coxkan/CoxKAN.py
coxkan/__init__.py
coxkan/hyperparam_search.py
coxkan/utils.py
coxkan/datasets/__init__.py
coxkan/datasets/_base.py
coxkan/datasets/deepsurv.py
coxkan/datasets/rdatasets.py
coxkan/datasets/simulation.py
coxkan-0.0.2.dist-info/LICENSE
coxkan-0.0.2.dist-info/METADATA
coxkan-0.0.2.dist-info/WHEEL
coxkan-0.0.2.dist-info/top_level.txt
coxkan-0.0.2.dist-info/RECORD
