Metadata-Version: 2.1
Name: coxkan
Version: 0.0.2
Summary: CoxKAN: Kolmogorov-Arnold Networks for Survival Analysis
Home-page: https://github.com/knottwill/CoxKAN
Author: William Knottenbelt
Author-email: knottenbeltwill@gmail.com
License: Apache License 2.0
Classifier: Programming Language :: Python :: 3
Classifier: License :: OSI Approved :: Apache Software License
Classifier: Operating System :: OS Independent
Requires-Python: >=3.6
License-File: LICENSE
Requires-Dist: pykan==0.0.2
Requires-Dist: lifelines>=0.28.0
Requires-Dist: torch>=2.3.1
Requires-Dist: tqdm
Requires-Dist: optuna>=3.6.1
Requires-Dist: torchtuples==0.2.2
Requires-Dist: scikit-learn>=1.5.0
Requires-Dist: feather-format>=0.4.0
Requires-Dist: h5py>=2.9.0
Requires-Dist: numba>=0.44
Requires-Dist: requests>=2.22.0
Requires-Dist: py7zr>=0.11.3
Requires-Dist: scipy>=1.13.1
